speed_cli/__init__.py
speed_cli/cli.py
speed_cli-0.2.0.dist-info/LICENSE
speed_cli-0.2.0.dist-info/METADATA
speed_cli-0.2.0.dist-info/WHEEL
speed_cli-0.2.0.dist-info/RECORD
