Metadata-Version: 2.1
Name: speed-cli
Version: 0.2.0
Summary: Effortlessly create descriptive, colorized command line interfaces (CLIs) for your script collections!
Home-page: https://github.com/Mnikley/Speed-CLI
License: MIT
Keywords: CLI,Command Line Interface,Script Collection Management,Package Management
Author: Matthias Ley
Author-email: matthias.ley@pm.me
Requires-Python: >=3.7,<4.0
Classifier: License :: OSI Approved :: MIT License
Classifier: Operating System :: OS Independent
Classifier: Programming Language :: Python :: 3
Classifier: Programming Language :: Python :: 3.7
Classifier: Programming Language :: Python :: 3.8
Classifier: Programming Language :: Python :: 3.9
Classifier: Programming Language :: Python :: 3.10
Classifier: Programming Language :: Python :: 3.11
Classifier: Programming Language :: Python :: 3 :: Only
Classifier: Programming Language :: Python :: 3.10
Classifier: Programming Language :: Python :: 3.11
Classifier: Programming Language :: Python :: 3.7
Classifier: Programming Language :: Python :: 3.8
Classifier: Programming Language :: Python :: 3.9
Classifier: Topic :: Software Development :: Libraries :: Python Modules
Project-URL: Repository, https://github.com/Mnikley/Speed-CLI
